setup.py
pyparts/__init__.py
pyparts/parts.py
pyparts.egg-info/PKG-INFO
pyparts.egg-info/SOURCES.txt
pyparts.egg-info/dependency_links.txt
pyparts.egg-info/entry_points.txt
pyparts.egg-info/not-zip-safe
pyparts.egg-info/pbr.json
pyparts.egg-info/requires.txt
pyparts.egg-info/top_level.txt