Metadata-Version: 1.1
Name: pyparts
Version: 0.5
Summary: Python electronic parts tool
Home-page: https://github.com/guyzmo/pyparts
Author: Bernard `Guyzmo` Pratz
Author-email: pyparts@m0g.net
License: GPLv3
Keywords: download tv show
Platform: UNKNOWN
Classifier: Programming Language :: Python :: 3
Classifier: Programming Language :: Python :: 3.4
Classifier: Development Status :: 4 - Beta
Classifier: License :: OSI Approved
Classifier: Operating System :: Unix
